cassandra_driver-3.29.3.dist-info/RECORD
cassandra_driver-3.29.3.dist-info/WHEEL
cassandra_driver-3.29.3.dist-info/top_level.txt
cassandra_driver-3.29.3.dist-info/METADATA
cassandra_driver-3.29.3.dist-info/licenses/LICENSE
cassandra/bytesio.pxd
cassandra/marshal.py
cassandra/auth.py
cassandra/metrics.py
cassandra/concurrent.py
cassandra/cython_utils.pyx
cassandra/metadata.py
cassandra/query.py
cassandra/deserializers.pxd
cassandra/cython_marshal.pyx
cassandra/row_parser.pyx
cassandra/util.py
cassandra/timestamps.py
cassandra/numpy_parser.pyx
cassandra/cqltypes.py
cassandra/protocol.py
cassandra/parsing.pxd
cassandra/type_codes.pxd
cassandra/buffer.pxd
cassandra/__init__.py
cassandra/murmur3.py
cassandra/encoder.py
cassandra/cmurmur3.c
cassandra/cmurmur3.cpython-39-darwin.so
cassandra/connection.py
cassandra/cluster.py
cassandra/parsing.pyx
cassandra/cython_deps.py
cassandra/type_codes.py
cassandra/ioutils.pyx
cassandra/tuple.pxd
cassandra/numpyFlags.h
cassandra/segment.py
cassandra/obj_parser.pyx
cassandra/deserializers.pyx
cassandra/pool.py
cassandra/policies.py
cassandra/cython_utils.pxd
cassandra/bytesio.pyx
cassandra/io/asyncorereactor.py
cassandra/io/libevwrapper.c
cassandra/io/asyncioreactor.py
cassandra/io/twistedreactor.py
cassandra/io/__init__.py
cassandra/io/geventreactor.py
cassandra/io/libevwrapper.cpython-39-darwin.so
cassandra/io/libevreactor.py
cassandra/io/eventletreactor.py
cassandra/column_encryption/_policies.py
cassandra/column_encryption/policies.py
cassandra/graph/query.py
cassandra/graph/graphson.py
cassandra/graph/__init__.py
cassandra/graph/types.py
cassandra/.dylibs/libev.4.dylib
cassandra/cqlengine/functions.py
cassandra/cqlengine/usertype.py
cassandra/cqlengine/models.py
cassandra/cqlengine/query.py
cassandra/cqlengine/__init__.py
cassandra/cqlengine/columns.py
cassandra/cqlengine/connection.py
cassandra/cqlengine/management.py
cassandra/cqlengine/statements.py
cassandra/cqlengine/operators.py
cassandra/cqlengine/named.py
cassandra/datastax/__init__.py
cassandra/datastax/insights/registry.py
cassandra/datastax/insights/util.py
cassandra/datastax/insights/serializers.py
