Metadata-Version: 2.4
Name: cassandra-driver
Version: 3.29.3
Summary:  DataStax Driver for Apache Cassandra
Home-page: http://github.com/datastax/python-driver
Author: DataStax
Project-URL: Documentation, https://docs.datastax.com/en/developer/python-driver/latest/
Project-URL: Source, https://github.com/datastax/python-driver/
Project-URL: Issues, https://datastax-oss.atlassian.net/browse/PYTHON
Keywords: cassandra,cql,orm,dse,graph
Classifier: Development Status :: 5 - Production/Stable
Classifier: Intended Audience :: Developers
Classifier: License :: OSI Approved :: Apache Software License
Classifier: Natural Language :: English
Classifier: Operating System :: OS Independent
Classifier: Programming Language :: Python
Classifier: Programming Language :: Python :: 3.9
Classifier: Programming Language :: Python :: 3.10
Classifier: Programming Language :: Python :: 3.11
Classifier: Programming Language :: Python :: 3.12
Classifier: Programming Language :: Python :: 3.13
Classifier: Programming Language :: Python :: Implementation :: CPython
Classifier: Programming Language :: Python :: Implementation :: PyPy
Classifier: Topic :: Software Development :: Libraries :: Python Modules
License-File: LICENSE
Requires-Dist: geomet>=1.1
Provides-Extra: graph
Requires-Dist: gremlinpython==3.4.6; extra == "graph"
Provides-Extra: cle
Requires-Dist: cryptography>=42.0; extra == "cle"
Dynamic: author
Dynamic: classifier
Dynamic: description
Dynamic: description-content-type
Dynamic: home-page
Dynamic: keywords
Dynamic: license-file
Dynamic: project-url
Dynamic: provides-extra
Dynamic: requires-dist
Dynamic: summary
